{
    "prints": [
        {
            "id": 100,
            "name": "Urithiru",
            "picture": "assets/images/prints/urithiru.jpg",
            "description": ""
        },
        {
            "id": 29,
            "name": "Catan Robber",
            "picture": "assets/images/prints/catan-robber.jpg",
            "description": ""
        },
        {
            "id": 28,
            "name": "Rhom Sound Machine Wall Mount",
            "picture": "assets/images/prints/rhom-holder.jpg",
            "description": ""
        },
        {
            "id": 27,
            "name": "Baby Yoda Cookie Cutter",
            "picture": "assets/images/prints/cookie-cutter-baby-yoda.jpg",
            "description": ""
        },
        {
            "id": 26,
            "name": "Batman Cookie Cutter",
            "picture": "assets/images/prints/cookie-cutter-batman.jpg",
            "description": ""
        },
        {
            "id": 25,
            "name": "Baby Feet Cookie Cutter",
            "picture": "assets/images/prints/cookie-cutter-baby-feet.jpg",
            "description": ""
        },
        {
            "id": 24,
            "name": "Poop Emoji Cookie Cutter",
            "picture": "assets/images/prints/cookie-cutter-poop-emoji.jpg",
            "description": ""
        },
        {
            "id": 23,
            "name": "Kaladin Stormblessed",
            "picture": "assets/images/prints/kaladin-stormblessed.jpg",
            "description": ""
        },
        {
            "id": 21,
            "name": "Gold Orcarina",
            "picture": "assets/images/prints/orcarina-gold.jpg",
            "description": ""
        },
        {
            "id": 20,
            "name": "Orcarina",
            "picture": "assets/images/prints/orcarina.jpg",
            "description": ""
        },
        {
            "id": 19,
            "name": "Toothpaste Roller",
            "picture": "assets/images/prints/toothpaste-roller.jpg",
            "description": ""
        },
        {
            "id": 18,
            "name": "Ear Bug Holder",
            "picture": "assets/images/prints/ear-bud-holder.jpg",
            "description": ""
        },
        {
            "id": 17,
            "name": "Egg Separator",
            "picture": "assets/images/prints/egg-separator.jpg",
            "description": ""
        },
        {
            "id": 16,
            "name": "Battery Holder",
            "picture": "assets/images/prints/battery-holder.jpg",
            "description": ""
        },
        {
            "id": 15,
            "name": "Owl Cookie Cutter",
            "picture": "assets/images/prints/cookie-cutter-owl.jpg",
            "description": ""
        },
        {
            "id": 14,
            "name": "Bitcoin Coaster",
            "picture": "assets/images/prints/bitcoin-coaster.jpg",
            "description": ""
        },
        {
            "id": 13,
            "name": "Catan Player Organizer",
            "picture": "assets/images/prints/catan-player-organizer.jpg",
            "description": ""
        },
        {
            "id": 12,
            "name": "Catan Harbor Master",
            "picture": "assets/images/prints/catan-harbor-master.jpg",
            "description": ""
        },
        {
            "id": 11,
            "name": "Lord of Catan",
            "picture": "assets/images/prints/catan-lord-of-catan.jpg",
            "description": ""
        },
        {
            "id": 10,
            "name": "Balerina",
            "picture": "assets/images/prints/balerina.jpg",
            "description": ""
        },
        {
            "id": 9,
            "name": "Catan Largest Army",
            "picture": "assets/images/prints/catan-largest-army.jpg",
            "description": ""
        },
        {
            "id": 8,
            "name": "Catan Metropolises",
            "picture": "assets/images/prints/catan-metropolis.jpg",
            "description": ""
        },
        {
            "id": 7,
            "name": "Catan Knights and City Walls",
            "picture": "assets/images/prints/catan-cities-knights.jpg",
            "description": ""
        },
        {
            "id": 6,
            "name": "Catan Longest Road",
            "picture": "assets/images/prints/catan-longest-road.jpg",
            "description": ""
        },
        {
            "id": 5,
            "name": "Pi Zero Case",
            "picture": "assets/images/prints/raspberry-pi-zero-case.jpg",
            "description": ""
        },
        {
            "id": 4,
            "name": "Headphone holder",
            "picture": "assets/images/prints/headphone-holder.jpg",
            "description": ""
        },
        {
            "id": 3,
            "name": "Catan Geometric Robber",
            "picture": "assets/images/prints/catan-geo-robber.jpg",
            "description": ""
        },
        {
            "id": 2,
            "name": "baby-yoda",
            "picture": "assets/images/prints/baby-yoda.jpg",
            "description": ""
        },
        {
            "id": 1,
            "name": "Zombicide Hand",
            "picture": "assets/images/prints/zombicide-hand.jpg",
            "description": ""
        }
    ]
}